{
  "input_path": "data\\processed\\features_40.csv",
  "output_path": "data\\processed\\features_40_aug.csv",
  "output_aug_only": "data\\processed\\features_40_aug_only.csv",
  "base_samples": 117,
  "aug_samples": 234,
  "total_samples": 351,
  "multiplier": 3.0,
  "noise_scale": 0.02,
  "mixup_alpha": 0.4,
  "seed": 42,
  "num_cols": [
    "Variety",
    "Sample",
    "D_conv",
    "D_stress",
    "D_recovery",
    "Rank",
    "R460",
    "R520",
    "R580",
    "R660",
    "R710",
    "R730",
    "R760",
    "R780",
    "R810",
    "R850",
    "R900",
    "VI_NDVI",
    "VI_NDRE",
    "VI_EVI",
    "VI_SIPI",
    "VI_PRI",
    "VI_MTCI",
    "VI_GNDVI",
    "VI_NDWI",
    "BF(F440)",
    "GF(F520)",
    "RF(F690)",
    "FrF(f740)",
    "SR_F690_F740",
    "SR_F440_F690",
    "SR_F440_F520",
    "SR_F520_F690",
    "SR_F440_F740",
    "SR_F520_F740",
    "OJIP_FvFm",
    "OJIP_PIabs",
    "OJIP_TRo_RC",
    "OJIP_ETo_RC",
    "OJIP_Vi",
    "OJIP_Vj",
    "OJIP_ABS_RC_log",
    "OJIP_DIo_RC_log"
  ],
  "bool_cols": [
    "Trt_CK1",
    "Trt_D1",
    "Trt_RD2"
  ]
}